Workbook

Sheet Hoja1
D2: OT 1069 FERNANDA KRAUSS - COCINA CASA AA
B4: FECHA | C4: N° FACTURA | D4: PROVEEDOR | F4: MONTO NETO | G4: IVA | H4: TOTAL | I4: STATUS
B6: Gastos Provisionados PC | H6: =F6-F7 -> -2519962
B7: Material | F7: =SUM(F8:F28) -> 2519962 | G7: =SUM(G8:G28) -> 478792.78 | H7: =SUM(H8:H28) -> 2998754.8
G8: =F8*19% -> 0 | H8: =F8+G8 -> 0
B9: 46083 | C9: 57028 | D9: MADERAS TARAPACA SPA | E9: ROBLE AMERICANO CEPILLADO C4C 5X150X2.7 (CANT.20) | F9: 332940 | G9: =F9*19% -> 63258.6 | H9: =F9+G9 -> 396198.6
B10: 46087 | C10: 220412 | D10: QUINCAMAT | E10: ROLLO ENCHAPE ENCINA 21MM X 50MTS (CANT.02) | F10: =12597*2 -> 25194 | G10: =F10*19% -> 4786.86 | H10: =F10+G10 -> 29980.86
B11: 46093 | C11: 1582260 | D11: DVP, S.A. | E11: KIT CAJON GRASS NOVAPRO ONE BCO ICE BAJO 500 (CANT.13)/KIT CAJON GRASS NOVAPRO ONE BCO ICE ALTO 500 (CANT.3) | F11: 745800 | G11: =F11*19% -> 141702 | H11: =F11+G11 -> 887502
B12: 46093 | C12: 158630 | D12: PROVELCAR | E12: CORREDERAS OCULTA C S 350 M M (CANT. 04) | F12: 32269 | G12: =F12*19% -> 6131.11 | H12: =F12+G12 -> 38400.11
B13: 46094 | C13: 158724 | D13: PROVELCAR | E13: CANASTO NANO 400MM (CANT. 03) | F13: 80647 | G13: =F13*19% -> 15322.93 | H13: =F13+G13 -> 95969.93
B14: 46094 | C14: 20054608 | D14: IMPERIAL | E14: MELAMINA MDP VALLE NM 18MM 1.83X2.50 (CANT. 02)/ROLLO TAPACANTO PVC VALLE 22X0,45MM RO 25MT (CANT. 01) | F14: 116807 | G14: =F14*19% -> 22193.33 | H14: =F14+G14 -> 139000.33
B15: 46099 | C15: 221221 | D15: QUINCAMAT | E15: TAPACANTO PVC VALLE 21X0,4 (CANT.25MTS) | F15: 6093 | G15: =F15*19% -> 1157.67 | H15: =F15+G15 -> 7250.67
B16: 46099 | C16: 13537 | D16: EPA | E16: AGLOM.ENCINA/ENCINA 15MM (CANT.10)/MDF ENCINA/ENCINA 15MM (CANT.02) | F16: =519970+117432 -> 637402 | G16: =F16*19% -> 121106.38 | H16: =F16+G16 -> 758508.38
B17: 46112 | C17: 20099773 | D17: IMPERIAL | E17: CESTA EXT. 3 NIVELES P/MUEBLE C/S 30CMS KUTZ (CANT.01) | F17: 29403 | G17: =F17*19% -> 5586.57 | H17: =F17+G17 -> 34989.57
B18: 46113 | C18: 304046 | D18: HBT | E18: MANILLA TUCSON CAFÉ ANTIQU 160MM (CANT.40)/MANILLA CE NEGRO MATE 160/200MM (CANT. 07) | F18: 134578 | G18: =F18*19% -> 25569.82 | H18: =F18+G18 -> 160147.82
B19: 46114 | C19: 160228 | D19: PROVELCAR | E19: BASURERO BAJO LAVAPLATOS DOBLE (CANT.01) | F19: 46210 | G19: =F19*19% -> 8779.9 | H19: =F19+G19 -> 54989.9
B20: 46128 | C20: 35313 | D20: FORMAS WOOD | E20: CHAPA ENCINA ROJA PRIMERA 39X270X2 (CANT. 02) | F20: 14322 | G20: =F20*19% -> 2721.18 | H20: =F20+G20 -> 17043.18
B21: 46157 | C21: 78149 | D21: DPH HERRAJES | E21: ESPECIERO ANTRACITA DPH CIERRE SUAVE 300MM (CANT.01) | F21: 41597 | G21: =F21*19% -> 7903.43 | H21: =F21+G21 -> 49500.43
B22: 46161 | C22: 224810 | D22: QUINCAMAT | E22: CANTO PVC ACACIA 22 X 0.44 X 50MTS (CANT.01) | F22: 12605 | G22: =F22*19% -> 2394.95 | H22: =F22+G22 -> 14999.95
B23: 46168 | C23: 1663971 | D23: DAP DUCASSE DISEÑO LTDA | E23: TIRADORES POMO 25X21MM (CANT. 06) | F23: 15054 | G23: =F23*19% -> 2860.26 | H23: =F23+G23 -> 17914.26
B24: 46168 | C24: 1659300 | D24: DAP DUCASSE DISEÑO LTDA | E24: TIRADORES POMO 25X21MM (CANT. 06) | F24: 15054 | G24: =F24*19% -> 2860.26 | H24: =F24+G24 -> 17914.26
B25: 46190 | C25: 1659765 | D25: DAP DUCASSE DISEÑO LTDA | E25: TIRADORES POMO 25X21MM (CANT. 03) | F25: 7527 | G25: =F25*19% -> 1430.13 | H25: =F25+G25 -> 8957.13
D27: HBT | E27: BISAGRA RECTA CIERRE SUAVE CLIPTOP 110° UNID (CANT 67) STOCK FABRICA | F27: =2880*67 -> 192960 | G27: =F27*19% -> 36662.4 | H27: =F27+G27 -> 229622.4
D28: HBT | E28: PLANCHETA CLIPTOP EN CRUZ 5mm (CANT 67) STOCK FABRICA | F28: =500*67 -> 33500 | G28: =F28*19% -> 6365 | H28: =F28+G28 -> 39865
B30: Gastos Provisionados PC | H30: =F30-F31 -> -212011
B31: Electricidad | F31: =SUM(F32:F36) -> 212011 | G31: =SUM(G32:G36) -> 40282.09 | H31: =SUM(H32:H36) -> 252293.09
G32: =F32*19% -> 0 | H32: =F32+G32 -> 0
B33: 46097 | C33: 241121 | D33: LED STUDIO | E33: PERFIL PARA CINTA LED STUDIO EMBUTIDO PLANO 2 MTS NEGRO (CANT. 08) | F33: 53849 | G33: =F33*19% -> 10231.31 | H33: =F33+G33 -> 64080.31
B34: 46098 | C34: 36350 | D34: ASYCAR | E34: FUENTE DE PODER 23W 12V INTERIOR (CANT.01)/FUENTE DE PODER 50W 12V INTERIOR (CANT.01)/FUENTE DE PODER 75W 12V INTERIOR (CANT.01)/CINTA LED 2835 BCO CALIDO 9.6W 12V (CANT.15MTS) | F34: 97718 | G34: =F34*19% -> 18566.42 | H34: =F34+G34 -> 116284.42
B35: 46162 | C35: 247538 | D35: LED STUDIO | E35: PERFIL PARA CINTA LED STUDIO EMBUTIDO PLANO 2 MTS NEGRO (CANT. 08) | F35: 60444 | G35: =F35*19% -> 11484.36 | H35: =F35+G35 -> 71928.36
G36: =F36*19% -> 0 | H36: =F36+G36 -> 0
B37: Gastos Provisionados PC | H37: =F37-F38 -> -236952
B38: Pintura y Derivados | F38: =SUM(F39:F46) -> 236952 | G38: =SUM(G39:G46) -> 45020.88 | H38: =SUM(H39:H46) -> 281972.88
G39: =F39*19% -> 0 | H39: =F39+G39 -> 0
B40: 46076 | C40: 147752 | D40: ENKO CHILE | E40: APLICACIÓN TINTA O ACEITE C/ESTANDAR C/ACABADO | F40: 38700 | G40: =F40*19% -> 7353 | H40: =F40+G40 -> 46053 | I40: MUESTRAS
B41: 46090 | C41: 148419 | D41: ENKO CHILE | E41: DESARROLLO DE COLOR LACADO,TINTA,ACEITE Y OTROS | F41: 53700 | G41: =F41*19% -> 10203 | H41: =F41+G41 -> 63903 | I41: MUESTRAS
B42: 46113 | C42: 149563 | D42: ENKO CHILE | E42: DILUYENTE PU UNIVERSAL (CANT. 15LT) | F42: 51570 | G42: =F42*19% -> 9798.3 | H42: =F42+G42 -> 61368.3
B43: 46118 | C43: 149662 | D43: ENKO CHILE | E43: DESARROLLO DE COLOR LACADO,TINTA,ACEITE Y OTROS ZZLAB.T3 (CANT. 1UND) | F43: 17900 | G43: =F43*19% -> 3401 | H43: =F43+G43 -> 21301
B44: 46125 | C44: 149976 | D44: ENKO CHILE | E44: TINTA AQUALINE B/AGUA LISTA USO NOGAL EUROPEO(CANT.1LT) | F44: 5789 | G44: =F44*19% -> 1099.91 | H44: =F44+G44 -> 6888.91
B45: 46126 | C45: 150058 | D45: ENKO CHILE | E45: TINTA AQUALINE LISTA USO (CANT.20LT) | F45: 69293 | G45: =F45*19% -> 13165.67 | H45: =F45+G45 -> 82458.67
G46: =F46*19% -> 0 | H46: =F46+G46 -> 0
B47: PLANCHAS | F47: =SUM(F48:F52) -> 216040 | G47: =SUM(G48:G52) -> 41047.6 | H47: =SUM(H48:H52) -> 257087.6
G48: =F48*19% -> 0 | H48: =F48+G48 -> 0
D49: HAGELIN | E49: MELAMINA BLANCA 18MM (CANT 4) STOCK FABRICA | F49: =31900*4 -> 127600 | G49: =F49*19% -> 24244 | H49: =F49+G49 -> 151844
D50: HAGELIN | E50: MELAMINA BLANCA 15MM (CANT 1) STOCK FABRICA | F50: =24500*1 -> 24500 | G50: =F50*19% -> 4655 | H50: =F50+G50 -> 29155
D51: MADIMEX | E51: PINO SECO CEPILLADO 1X5"X320 (CANT 23) STOCK FABRICA | F51: =2780*23 -> 63940 | G51: =F51*19% -> 12148.6 | H51: =F51+G51 -> 76088.6
H52: =F52+G52 -> 0
B53: Gastos Provisionados PC | H53: =F53-F54 -> 0
B54: Fierro - Alambre | F54: =SUM(F56:F59) -> 0 | G54: =SUM(G56:G59) -> 0 | H54: =SUM(H56:H59) -> 0
G59: =F59*19% -> 0 | H59: =F59+G59 -> 0
B60: Taller - Herramientas | F60: =SUM(F61:F63) -> 0 | G60: =SUM(G61:G63) -> 0 | H60: =SUM(H61:H63) -> 0
G61: =F61*19% -> 0 | H61: =F61+G61 -> 0
B64: Gastos Provisionados PC | H64: =F64-F65 -> -3071572
B65: Mano de obra externa - Otros | F65: =SUM(F66:F69) -> 3071572 | G65: =SUM(G66:G69) -> 583598.68 | H65: =SUM(H66:H69) -> 3655170.7
G66: =F66*19% -> 0 | H66: =F66+G66 -> 0
B67: 46108 | C67: 8367 | D67: VIALIM | E67: PUERTAS V20 NEGRO VIDRIO INCOLORO (CANT. 07) | F67: 357820 | G67: =F67*19% -> 67985.8 | H67: =F67+G67 -> 425805.8
B68: 46119 | C68: 26999 | D68: CASA MURA | E68: CUBIERTA CALACATTA PERLA (CANT.04)/DIMENSIONADO CUARZO (CANT. 04) | F68: 1921152 | G68: =F68*19% -> 365018.88 | H68: =F68+G68 -> 2286170.9
B69: 46146 | C69: 66 | D69: APEDRA | E69: FABRICACIÓN E INSTALACIÓN CUBIERTA CALACATTA PERLA 15MM | F69: 792600 | G69: =F69*19% -> 150594 | H69: =F69+G69 -> 943194
F70: 0 | G70: =F70*19% -> 0 | H70: =F70+G70 -> 0
B71: Colaciones - Instalaciones - Despacho | F71: =SUM(F72:F78) -> 0 | G71: =SUM(G72:G78) -> 0 | H71: =SUM(H72:H78) -> 0
F72: =E72*19% -> 0 | G72: =E72+F72 -> 0
B80: TOTAL G. PRODUCCION | C80: =E91 -> 11537116 | D80: (NETO)
B81: TOTAL COBRADO | C81: 29869454 | D81: (NETO)
B82: DIFERENCIA | C82: =C81-C80 -> 18332338
C85: PC | D85: COBRADO | E85: REAL | F85: GANANCIA PC | H85: UTILIDAD
B86: COSTO MAT.PC | C86: =6305719+1405000+1157500 -> 8868219 | D86: =13971327+2094814+4280589 -> 20346730 | E86: =F7+F31+F38+F47 -> 3184965 | F86: =C86-E86 -> 5683254 | G86: =C86-E86-E89 -> 2611682 | H86: =D86-E86-E87-E89-E90 -> 10024614 | K86: =E86+E89 -> 6256537 | L86: =C86 -> 8868219 | M86: =(K86/L86) -> 0.70550096
B87: MANO DE OBRA PC | C87: =3235000+30000+820000 -> 4085000 | D87: 0 | E87: =C109 -> 3016750 | F87: =C87-E87 -> 1068250 | G87: =C87-E87 -> 1068250
B88: GASTOS INSTALACION | C88: 1915000 | D88: 2583750 | E88: =C126+F71+C133 -> 1215000 | F88: =C88-E88 -> 700000 | H88: =D88-E88 -> 1368750
B89: MANO DE OBRA EXTERNA | C89: =4716819+50000 -> 4766819 | D89: 6938974 | E89: =F65 -> 3071572 | F89: =C89-E89 -> 1695247
B90: GASTOS ADMINISTRATIVOS | C90: =477036+71750+98875+238341 -> 886002 | D90: 0 | E90: =(E86+E87+E88+E89)*10% -> 1048828.7 | F90: =C90-E90 -> -162826.7
B91: TOTAL REAL | E91: =SUM(E86:E90) -> 11537116 | F91: =SUM(F86:F90) -> 8983924.3 | H91: =SUM(H86:H90) -> 11393364
H93: PC
B94: Mano de Obra 10.03 al 15.06.26 | F94: DIAS FABRICACION | G94: 51 | H94: 74 | I94: =H94-G94 -> 23
B95: ALDO ROMERO
B96: ALEJANDRO ALVAREZ | F96: EXTRAS | G96: 34
B97: ALEJANDRO SANCHEZ
B98: ALAN BURGOS | C98: =36000*13+15000*10+50000*3 -> 768000 | D98: 13dia+11extras+3sab | F98: SABADOS | G98: 9
B99: DAVID MOLINA | C99: =30000*12+15000*14+50000*3 -> 720000 | D99: 12dias+14extras+3sab
B100: HECTOR BARAHONA | F100: FERIADOS - DOMINGO
B101: HERNANDO SALDIAS | C101: =48000*3 -> 144000 | D101: 3dias
B102: JUAN LOBOS | C102: =42000*4 -> 168000 | D102: 4dias | F102: INSTALACION | G102: 29 | H102: 30 | I102: =H102-G102 -> 1
B103: MARCELO ESPINA | C103: =48000*10+24000+15000*9+50000*2+25000 -> 764000 | D103: 10dias+mediodia+9extras+2sab y medio
B104: MIGUEL ROMERO
B105: YEFERSON BARRIOS
B106: JOHAN FERRER | C106: =48000*8+18750+50000 -> 452750 | D106: 8dias+mediodia+1sab
B107: JONAS GONZALES
B108: PEDRO MENESES
C109: =SUM(C95:C108) -> 3016750
B111: Instalación 25.03 al 15.06
B112: ALDO ROMERO
B113: ALEJANDRO ALVAREZ
B114: ALEJANDRO SANCHEZ
B115: ALAN BURGOS | C115: =36000*4 -> 144000 | D115: 4dia
B116: DAVID MOLINA | C116: =30000*11+15000 -> 345000 | D116: 11dias+mediodia
B117: HECTOR BARAHONA
B118: HERNANDO SALDIAS
B119: JUAN LOBOS
B120: MARCELO ESPINA | C120: =48000*12+24000+48000 -> 648000 | D120: 12dias+mediodia+visita
B121: MIGUEL ROMERO | C121: =39000*2 -> 78000 | D121: 1dias+visita
B122: YEFERSON BARRIOS
...

Sheet Análisis Proyecto
A1: ANÁLISIS FINANCIERO · OT 1069
A2: Fernanda Krauss · Cocina Casa AA | análisis neto, vinculado a Hoja1
A4: INGRESO NETO | C4: COSTO REAL | E4: UTILIDAD REAL | G4: MARGEN REAL
A5: =Hoja1!C81 -> 29869454 | C5: =Hoja1!E91 -> 11537116 | E5: =Hoja1!C81-Hoja1!E91 -> 18332338 | G5: =(Hoja1!C81-Hoja1!E91)/Hoja1!C81 -> 0.61374869
A8: PRESUPUESTO DE COSTOS | C8: AHORRO VS PC | E8: DESVIACIÓN FAVORABLE | G8: UTILIDAD MOSTRADA EN FUENTE
A9: =SUM(Hoja1!C86:C90) -> 20521040 | C9: =SUM(Hoja1!C86:C90)-Hoja1!E91 -> 8983924.3 | E9: =(SUM(Hoja1!C86:C90)-Hoja1!E91)/SUM(Hoja1!C86:C90) -> 0.43779089 | G9: =Hoja1!H91 -> 11393364
A11: DESEMPEÑO POR CATEGORÍA
A12: Categoría | B12: PC | C12: Real | D12: Variación $ | E12: Variación % | F12: Estado
A13: Materiales | B13: =Hoja1!C86 -> 8868219 | C13: =Hoja1!E86 -> 3184965 | D13: =B13-C13 -> 5683254 | E13: =IFERROR(D13/B13,0) -> 0.6408563 | F13: =IF(D13>=0,"Favorable","Sobrecosto") -> Favorable
A14: Mano de obra | B14: =Hoja1!C87 -> 4085000 | C14: =Hoja1!E87 -> 3016750 | D14: =B14-C14 -> 1068250 | E14: =IFERROR(D14/B14,0) -> 0.26150551 | F14: =IF(D14>=0,"Favorable","Sobrecosto") -> Favorable
A15: Instalación | B15: =Hoja1!C88 -> 1915000 | C15: =Hoja1!E88 -> 1215000 | D15: =B15-C15 -> 700000 | E15: =IFERROR(D15/B15,0) -> 0.36553525 | F15: =IF(D15>=0,"Favorable","Sobrecosto") -> Favorable
A16: Mano de obra externa | B16: =Hoja1!C89 -> 4766819 | C16: =Hoja1!E89 -> 3071572 | D16: =B16-C16 -> 1695247 | E16: =IFERROR(D16/B16,0) -> 0.35563486 | F16: =IF(D16>=0,"Favorable","Sobrecosto") -> Favorable
A17: Gastos administrativos | B17: =Hoja1!C90 -> 886002 | C17: =Hoja1!E90 -> 1048828.7 | D17: =B17-C17 -> -162826.7 | E17: =IFERROR(D17/B17,0) -> -0.1837769 | F17: =IF(D17>=0,"Favorable","Sobrecosto") -> Sobrecosto
A18: TOTAL | B18: =SUM(B13:B17) -> 20521040 | C18: =SUM(C13:C17) -> 11537116 | D18: =B18-C18 -> 8983924.3 | E18: =IFERROR(D18/B18,0) -> 0.43779089 | F18: =IF(D18>=0,"Favorable","Sobrecosto") -> Favorable
A21: CONTROL DOCUMENTAL
A22: Indicador | B22: Resultado | D22: Indicador | E22: Resultado
A23: Movimientos detallados | B23: =COUNTIF(Hoja1!F9:F28,">0")+COUNTIF(Hoja1!F33:F35,">0")+COUNTIF(Hoja1!F40:F45,">0")+COUNTIF(Hoja1!F49:F51,">0")+COUNTIF(Hoja1!F67:F69,">0") -> 34 | D23: Cobertura fecha | E23: =IFERROR(B24/B23,0) -> 0.85294118
A24: Con fecha | B24: =COUNT(Hoja1!B9:B28)+COUNT(Hoja1!B33:B35)+COUNT(Hoja1!B40:B45)+COUNT(Hoja1!B49:B51)+COUNT(Hoja1!B67:B69) -> 29 | D24: Cobertura factura | E24: =IFERROR(B25/B23,0) -> 0.85294118
A25: Con N° factura | B25: =COUNT(Hoja1!C9:C28)+COUNT(Hoja1!C33:C35)+COUNT(Hoja1!C40:C45)+COUNT(Hoja1!C49:C51)+COUNT(Hoja1!C67:C69) -> 29 | D25: Cobertura status | E25: =IFERROR(B26/B23,0) -> 0.058823529
A26: Con status | B26: =COUNTA(Hoja1!I9:I28)+COUNTA(Hoja1!I33:I35)+COUNTA(Hoja1!I40:I45)+COUNTA(Hoja1!I49:I51)+COUNTA(Hoja1!I67:I69) -> 2 | D26: Muestras incluidas (neto) | E26: =SUM(Hoja1!F40:F41) -> 92400
A29: HALLAZGOS CLAVE
A30: 1. Utilidad corregida: Hoja1!H91 no incorpora los $6.938.974 cobrados por mano de obra externa.
A31: 2. Costos reales 43,8% bajo PC; materiales explican $5.683.254 del ahorro total.
A32: 3. Gastos administrativos exceden el PC en $162.827 (+18,4%); es la única categoría desfavorable.
A33: 4. Solo 2 de 34 movimientos tienen STATUS; 5 movimientos de stock no tienen fecha ni N° de factura.
A34: 5. $92.400 netos de muestras están incluidos en Pintura; conviene validar si son imputables al proyecto.
